CHANGES.txt
MANIFEST.in
README.txt
setup.cfg
setup.py
ponzi_evolution/__init__.py
ponzi_evolution/test.py
ponzi_evolution.egg-info/PKG-INFO
ponzi_evolution.egg-info/SOURCES.txt
ponzi_evolution.egg-info/dependency_links.txt
ponzi_evolution.egg-info/entry_points.txt
ponzi_evolution.egg-info/not-zip-safe
ponzi_evolution.egg-info/requires.txt
ponzi_evolution.egg-info/top_level.txt
ponzi_evolution/evolve/__init__.py
ponzi_evolution/evolve/evolve1.py