Metadata-Version: 1.0
Name: ponzi-evolution
Version: 0.8998
Summary: Dead simple schema upgrades for SQLAlchemy.
Home-page: http://bitbucket.org/dholth/ponzi_evolution
Author: Daniel Holth
Author-email: dholth@fastmail.fm
License: UNKNOWN
Keywords: sqlalchemy
Platform: UNKNOWN
Classifier: Programming Language :: Python
Classifier: Framework :: Pylons
Classifier: Topic :: Internet :: WWW/HTTP
Classifier: Topic :: Internet :: WWW/HTTP :: WSGI :: Application
